[
  {
    "firstName": "Chloe",
    "lastName": "Skorpen",
    "email": "chloe.skorpen@example.com",
    "username": "heavyladybug739",
    "password": "stone",
    "invokedAt": "2021-11-12T01:45:45.135Z"
  },
  {
    "firstName": "Isabel",
    "lastName": "Hughes",
    "email": "isabel.hughes@example.com",
    "username": "angryrabbit586",
    "password": "lamer",
    "invokedAt": "2021-11-12T02:18:57.290Z"
  },
  {
    "firstName": "Özkan",
    "lastName": "Fahri",
    "email": "ozkan.fahri@example.com",
    "username": "whitemeercat110",
    "password": "vampires",
    "invokedAt": "2021-11-12T02:58:48.646Z"
  },
  {
    "firstName": "Katia",
    "lastName": "Robert",
    "email": "katia.robert@example.com",
    "username": "sadfrog574",
    "password": "cwoui",
    "invokedAt": "2021-11-12T03:58:48.741Z"
  },
  {
    "firstName": "Jozias",
    "lastName": "Ermens",
    "email": "jozias.ermens@example.com",
    "username": "organicwolf648",
    "password": "mollie",
    "invokedAt": "2021-11-12T05:00:30.840Z"
  },
  {
    "firstName": "Léonie",
    "lastName": "Roger",
    "email": "leonie.roger@example.com",
    "username": "bluebutterfly377",
    "password": "635241",
    "invokedAt": "2021-11-12T05:59:15.803Z"
  },
  {
    "firstName": "Afşar",
    "lastName": "Kuday",
    "email": "afsar.kuday@example.com",
    "username": "heavywolf170",
    "password": "topdog",
    "invokedAt": "2021-11-12T06:58:55.329Z"
  },
  {
    "firstName": "Carola",
    "lastName": "Roger",
    "email": "carola.roger@example.com",
    "username": "silverpeacock129",
    "password": "buckshot",
    "invokedAt": "2021-11-12T07:59:14.906Z"
  },
  {
    "firstName": "Arnold",
    "lastName": "Mendoza",
    "email": "arnold.mendoza@example.com",
    "username": "crazycat908",
    "password": "zorro",
    "invokedAt": "2021-11-12T08:58:55.884Z"
  },
  {
    "firstName": "Eduardo",
    "lastName": "Rubio",
    "email": "eduardo.rubio@example.com",
    "username": "tinybear844",
    "password": "marcel",
    "invokedAt": "2021-11-12T09:58:51.410Z"
  },
  {
    "firstName": "Hanna",
    "lastName": "Martin",
    "email": "hanna.martin@example.com",
    "username": "happybutterfly581",
    "password": "0.0.000",
    "invokedAt": "2021-11-12T10:59:02.221Z"
  },
  {
    "firstName": "Charlotte",
    "lastName": "Douglas",
    "email": "charlotte.douglas@example.com",
    "username": "sadfish425",
    "password": "overkill",
    "invokedAt": "2021-11-12T11:59:06.769Z"
  },
  {
    "firstName": "Jan",
    "lastName": "Røgeberg",
    "email": "jan.rogeberg@example.com",
    "username": "silverlion568",
    "password": "bigone",
    "invokedAt": "2021-11-12T13:10:57.494Z"
  }
]