[
  {
    "firstName": "Valentin",
    "lastName": "Morales",
    "email": "valentin.morales@example.com",
    "username": "blackgoose119",
    "password": "stiletto",
    "invokedAt": "2021-06-10T02:04:34.029Z"
  },
  {
    "firstName": "Matthew",
    "lastName": "Evans",
    "email": "matthew.evans@example.com",
    "username": "ticklishwolf890",
    "password": "busty",
    "invokedAt": "2021-06-10T03:20:17.257Z"
  },
  {
    "firstName": "Mario",
    "lastName": "David",
    "email": "mario.david@example.com",
    "username": "smalltiger146",
    "password": "bossman",
    "invokedAt": "2021-06-10T04:15:10.670Z"
  },
  {
    "firstName": "Florence",
    "lastName": "Robinson",
    "email": "florence.robinson@example.com",
    "username": "saddog399",
    "password": "deedee",
    "invokedAt": "2021-06-10T05:23:04.334Z"
  }
]