[
  {
    "firstName": "اميرمحمد",
    "lastName": "محمدخان",
    "email": "myrmhmd.mhmdkhn@example.com",
    "username": "heavyswan808",
    "password": "town",
    "invokedAt": "2021-09-30T01:54:22.986Z"
  },
  {
    "firstName": "Samantha",
    "lastName": "Nguyen",
    "email": "samantha.nguyen@example.com",
    "username": "bigladybug966",
    "password": "computer",
    "invokedAt": "2021-09-30T02:25:41.705Z"
  },
  {
    "firstName": "Tom",
    "lastName": "Welch",
    "email": "tom.welch@example.com",
    "username": "yellowsnake627",
    "password": "indian",
    "invokedAt": "2021-09-30T02:59:02.459Z"
  },
  {
    "firstName": "Elli",
    "lastName": "Manninen",
    "email": "elli.manninen@example.com",
    "username": "brownostrich243",
    "password": "4567",
    "invokedAt": "2021-09-30T03:58:51.926Z"
  },
  {
    "firstName": "Allie",
    "lastName": "Turner",
    "email": "allie.turner@example.com",
    "username": "goldenzebra288",
    "password": "stephane",
    "invokedAt": "2021-09-30T04:59:40.625Z"
  },
  {
    "firstName": "Frederik",
    "lastName": "Poulsen",
    "email": "frederik.poulsen@example.com",
    "username": "purplepeacock974",
    "password": "fellow",
    "invokedAt": "2021-09-30T05:59:27.176Z"
  },
  {
    "firstName": "Sofie",
    "lastName": "Takle",
    "email": "sofie.takle@example.com",
    "username": "bluepanda412",
    "password": "howard",
    "invokedAt": "2021-09-30T06:58:56.137Z"
  }
]