[
  {
    "firstName": "Rosa",
    "lastName": "Wheeler",
    "email": "rosa.wheeler@example.com",
    "username": "bluebird529",
    "password": "steelers",
    "invokedAt": "2021-12-13T01:48:58.361Z"
  },
  {
    "firstName": "Werner",
    "lastName": "Adam",
    "email": "werner.adam@example.com",
    "username": "tinypeacock769",
    "password": "lady",
    "invokedAt": "2021-12-13T02:22:35.052Z"
  },
  {
    "firstName": "Begoña",
    "lastName": "Garrido",
    "email": "begona.garrido@example.com",
    "username": "happyfrog205",
    "password": "teddybea",
    "invokedAt": "2021-12-13T02:59:20.764Z"
  },
  {
    "firstName": "James",
    "lastName": "Ouellet",
    "email": "james.ouellet@example.com",
    "username": "orangemouse860",
    "password": "cars",
    "invokedAt": "2021-12-13T03:58:52.534Z"
  },
  {
    "firstName": "Adam",
    "lastName": "Andersen",
    "email": "adam.andersen@example.com",
    "username": "blackfish187",
    "password": "thumb",
    "invokedAt": "2021-12-13T05:00:58.727Z"
  },
  {
    "firstName": "Joshua",
    "lastName": "Hudson",
    "email": "joshua.hudson@example.com",
    "username": "yellowswan650",
    "password": "deer",
    "invokedAt": "2021-12-13T05:59:25.857Z"
  },
  {
    "firstName": "Gregorius",
    "lastName": "Lakeman",
    "email": "gregorius.lakeman@example.com",
    "username": "happyswan583",
    "password": "simpson",
    "invokedAt": "2021-12-13T06:58:52.118Z"
  },
  {
    "firstName": "Maël",
    "lastName": "Perez",
    "email": "mael.perez@example.com",
    "username": "crazyleopard323",
    "password": "colorado",
    "invokedAt": "2021-12-13T07:59:17.790Z"
  },
  {
    "firstName": "Ceylan",
    "lastName": "Topçuoğlu",
    "email": "ceylan.topcuoglu@example.com",
    "username": "crazyladybug562",
    "password": "alaska",
    "invokedAt": "2021-12-13T08:58:51.243Z"
  },
  {
    "firstName": "Isolda",
    "lastName": "Santos",
    "email": "isolda.santos@example.com",
    "username": "happyleopard377",
    "password": "whiskey",
    "invokedAt": "2021-12-13T09:59:03.504Z"
  },
  {
    "firstName": "Blanca",
    "lastName": "Cruz",
    "email": "blanca.cruz@example.com",
    "username": "goldendog354",
    "password": "video",
    "invokedAt": "2021-12-13T10:59:07.774Z"
  },
  {
    "firstName": "Murat",
    "lastName": "Dalkıran",
    "email": "murat.dalkiran@example.com",
    "username": "ticklishpeacock110",
    "password": "slim",
    "invokedAt": "2021-12-13T11:59:17.073Z"
  },
  {
    "firstName": "سام",
    "lastName": "کوتی",
    "email": "sm.khwty@example.com",
    "username": "silverpanda844",
    "password": "honolulu",
    "invokedAt": "2021-12-13T13:12:10.197Z"
  },
  {
    "firstName": "Jeremy",
    "lastName": "Cunningham",
    "email": "jeremy.cunningham@example.com",
    "username": "whiteladybug755",
    "password": "italian",
    "invokedAt": "2021-12-13T13:59:00.649Z"
  },
  {
    "firstName": "Veera",
    "lastName": "Laine",
    "email": "veera.laine@example.com",
    "username": "silvermouse400",
    "password": "curtis",
    "invokedAt": "2021-12-13T14:58:54.463Z"
  },
  {
    "firstName": "Addison",
    "lastName": "Singh",
    "email": "addison.singh@example.com",
    "username": "sadmouse441",
    "password": "conrad",
    "invokedAt": "2021-12-13T15:59:03.215Z"
  },
  {
    "firstName": "Ceyhan",
    "lastName": "Tazegül",
    "email": "ceyhan.tazegul@example.com",
    "username": "happyduck775",
    "password": "nope",
    "invokedAt": "2021-12-13T17:15:34.546Z"
  },
  {
    "firstName": "Chiara",
    "lastName": "Clement",
    "email": "chiara.clement@example.com",
    "username": "beautifulsnake981",
    "password": "emily1",
    "invokedAt": "2021-12-13T17:58:48.164Z"
  },
  {
    "firstName": "Muhammad",
    "lastName": "Kaijser",
    "email": "muhammad.kaijser@example.com",
    "username": "sadfrog241",
    "password": "eileen",
    "invokedAt": "2021-12-13T18:59:12.783Z"
  },
  {
    "firstName": "Donald",
    "lastName": "Stephens",
    "email": "donald.stephens@example.com",
    "username": "smallbear365",
    "password": "hhhhhhh",
    "invokedAt": "2021-12-13T19:58:58.373Z"
  },
  {
    "firstName": "James",
    "lastName": "Sullivan",
    "email": "james.sullivan@example.com",
    "username": "greenfrog175",
    "password": "payton",
    "invokedAt": "2021-12-13T20:58:53.870Z"
  },
  {
    "firstName": "Rosmarie",
    "lastName": "Guillaume",
    "email": "rosmarie.guillaume@example.com",
    "username": "sadtiger638",
    "password": "monty1",
    "invokedAt": "2021-12-13T21:59:21.897Z"
  },
  {
    "firstName": "John",
    "lastName": "Li",
    "email": "john.li@example.com",
    "username": "greenfrog625",
    "password": "egghead",
    "invokedAt": "2021-12-13T22:59:02.015Z"
  }
]