[
  {
    "firstName": "Reginald",
    "lastName": "Cole",
    "email": "reginald.cole@example.com",
    "username": "heavytiger742",
    "password": "sigma",
    "invokedAt": "2021-04-04T00:00:18.690Z"
  },
  {
    "firstName": "Christoph",
    "lastName": "Erens",
    "email": "christoph.erens@example.com",
    "username": "heavykoala211",
    "password": "ssss",
    "invokedAt": "2021-04-04T01:57:15.452Z"
  },
  {
    "firstName": "Cecilie",
    "lastName": "Sørensen",
    "email": "cecilie.sorensen@example.com",
    "username": "blacktiger403",
    "password": "6666",
    "invokedAt": "2021-04-04T03:14:03.700Z"
  },
  {
    "firstName": "Charles",
    "lastName": "Walker",
    "email": "charles.walker@example.com",
    "username": "lazycat598",
    "password": "onions",
    "invokedAt": "2021-04-04T04:02:13.105Z"
  },
  {
    "firstName": "Adam",
    "lastName": "Smith",
    "email": "adam.smith@example.com",
    "username": "beautifulwolf587",
    "password": "golf",
    "invokedAt": "2021-04-04T05:12:30.846Z"
  },
  {
    "firstName": "Gene",
    "lastName": "Herrera",
    "email": "gene.herrera@example.com",
    "username": "crazymeercat970",
    "password": "capone",
    "invokedAt": "2021-04-04T05:57:07.951Z"
  },
  {
    "firstName": "Soledad",
    "lastName": "Serrano",
    "email": "soledad.serrano@example.com",
    "username": "beautifulswan889",
    "password": "original",
    "invokedAt": "2021-04-04T07:09:44.791Z"
  },
  {
    "firstName": "Flynn",
    "lastName": "Roberts",
    "email": "flynn.roberts@example.com",
    "username": "purplebear290",
    "password": "tony",
    "invokedAt": "2021-04-04T07:57:11.443Z"
  },
  {
    "firstName": "Mestan",
    "lastName": "Yorulmaz",
    "email": "mestan.yorulmaz@example.com",
    "username": "angryrabbit931",
    "password": "caravan",
    "invokedAt": "2021-04-04T08:59:02.011Z"
  },
  {
    "firstName": "Donna",
    "lastName": "Robertson",
    "email": "donna.robertson@example.com",
    "username": "bigbird778",
    "password": "acer",
    "invokedAt": "2021-04-04T10:03:42.205Z"
  },
  {
    "firstName": "Mason",
    "lastName": "Williams",
    "email": "mason.williams@example.com",
    "username": "blackmeercat230",
    "password": "cutter",
    "invokedAt": "2021-04-04T11:03:48.373Z"
  },
  {
    "firstName": "آوین",
    "lastName": "احمدی",
    "email": "awyn.hmdy@example.com",
    "username": "organicfrog546",
    "password": "remingto",
    "invokedAt": "2021-04-04T11:57:14.836Z"
  },
  {
    "firstName": "Morgan",
    "lastName": "Van de Putte",
    "email": "morgan.vandeputte@example.com",
    "username": "silverbear493",
    "password": "alyssa",
    "invokedAt": "2021-04-04T13:14:43.444Z"
  },
  {
    "firstName": "Vedat",
    "lastName": "Keçeci",
    "email": "vedat.kececi@example.com",
    "username": "happygorilla888",
    "password": "isabella",
    "invokedAt": "2021-04-04T13:57:12.604Z"
  },
  {
    "firstName": "Nila",
    "lastName": "Gjeruldsen",
    "email": "nila.gjeruldsen@example.com",
    "username": "greengorilla486",
    "password": "cooper",
    "invokedAt": "2021-04-04T14:57:12.584Z"
  },
  {
    "firstName": "Caroline",
    "lastName": "Elliott",
    "email": "caroline.elliott@example.com",
    "username": "sadpanda963",
    "password": "eric",
    "invokedAt": "2021-04-04T16:01:13.298Z"
  },
  {
    "firstName": "Begüm",
    "lastName": "Ekici",
    "email": "begum.ekici@example.com",
    "username": "brownbird592",
    "password": "joecool",
    "invokedAt": "2021-04-04T17:35:46.490Z"
  },
  {
    "firstName": "Frank",
    "lastName": "Hunt",
    "email": "frank.hunt@example.com",
    "username": "whitemouse852",
    "password": "pppppppp",
    "invokedAt": "2021-04-04T18:19:51.086Z"
  },
  {
    "firstName": "Nooa",
    "lastName": "Nevala",
    "email": "nooa.nevala@example.com",
    "username": "greenbutterfly955",
    "password": "dilbert",
    "invokedAt": "2021-04-04T19:12:11.609Z"
  }
]