[
  {
    "firstName": "Edward",
    "lastName": "Porter",
    "email": "edward.porter@example.com",
    "username": "heavyleopard776",
    "password": "jackoff",
    "invokedAt": "2021-06-09T00:00:15.304Z"
  },
  {
    "firstName": "مریم",
    "lastName": "سهيلي راد",
    "email": "mrym.shylyrd@example.com",
    "username": "angrydog571",
    "password": "patricia",
    "invokedAt": "2021-06-09T02:07:53.383Z"
  },
  {
    "firstName": "Elzira",
    "lastName": "Duarte",
    "email": "elzira.duarte@example.com",
    "username": "ticklishrabbit677",
    "password": "huge",
    "invokedAt": "2021-06-09T03:27:07.903Z"
  },
  {
    "firstName": "Silje",
    "lastName": "Rasmussen",
    "email": "silje.rasmussen@example.com",
    "username": "ticklishpanda643",
    "password": "water1",
    "invokedAt": "2021-06-09T04:22:49.853Z"
  },
  {
    "firstName": "Jesse",
    "lastName": "Koskinen",
    "email": "jesse.koskinen@example.com",
    "username": "blackpeacock814",
    "password": "viagra",
    "invokedAt": "2021-06-09T05:26:48.332Z"
  },
  {
    "firstName": "Eli",
    "lastName": "Li",
    "email": "eli.li@example.com",
    "username": "yellowcat529",
    "password": "kelly1",
    "invokedAt": "2021-06-09T06:13:14.440Z"
  },
  {
    "firstName": "هلیا",
    "lastName": "رضاییان",
    "email": "hly.rdyyn@example.com",
    "username": "yellowcat612",
    "password": "catcat",
    "invokedAt": "2021-06-09T07:15:00.544Z"
  },
  {
    "firstName": "Kate",
    "lastName": "Gibson",
    "email": "kate.gibson@example.com",
    "username": "goldenmouse191",
    "password": "piper",
    "invokedAt": "2021-06-09T08:00:11.940Z"
  },
  {
    "firstName": "Gloria",
    "lastName": "Hart",
    "email": "gloria.hart@example.com",
    "username": "crazycat797",
    "password": "cheyenne",
    "invokedAt": "2021-06-09T08:59:38.499Z"
  },
  {
    "firstName": "Lance",
    "lastName": "Barnes",
    "email": "lance.barnes@example.com",
    "username": "purplemeercat363",
    "password": "tabatha",
    "invokedAt": "2021-06-09T09:59:21.130Z"
  },
  {
    "firstName": "Katarina",
    "lastName": "Nieuwkerk",
    "email": "katarina.nieuwkerk@example.com",
    "username": "angrydog480",
    "password": "albert",
    "invokedAt": "2021-06-09T11:00:39.607Z"
  },
  {
    "firstName": "Antelmo",
    "lastName": "Ferreira",
    "email": "antelmo.ferreira@example.com",
    "username": "beautifulkoala406",
    "password": "cody",
    "invokedAt": "2021-06-09T11:57:18.356Z"
  },
  {
    "firstName": "Sofie",
    "lastName": "Møller",
    "email": "sofie.moller@example.com",
    "username": "sadwolf241",
    "password": "billbill",
    "invokedAt": "2021-06-09T13:19:52.056Z"
  },
  {
    "firstName": "Philip",
    "lastName": "Sørensen",
    "email": "philip.sorensen@example.com",
    "username": "ticklishpanda183",
    "password": "anchor",
    "invokedAt": "2021-06-09T14:04:32.767Z"
  }
]