[
  {
    "firstName": "Pinja",
    "lastName": "Keto",
    "email": "pinja.keto@example.com",
    "username": "brownbutterfly160",
    "password": "radio",
    "invokedAt": "2021-11-07T01:48:29.887Z"
  },
  {
    "firstName": "Kenzi",
    "lastName": "Morris",
    "email": "kenzi.morris@example.com",
    "username": "lazyostrich157",
    "password": "solitude",
    "invokedAt": "2021-11-07T02:20:47.667Z"
  },
  {
    "firstName": "Maiko",
    "lastName": "Steins",
    "email": "maiko.steins@example.com",
    "username": "greenbear643",
    "password": "warner",
    "invokedAt": "2021-11-07T02:58:51.320Z"
  },
  {
    "firstName": "Tjipke",
    "lastName": "Andela",
    "email": "tjipke.andela@example.com",
    "username": "angrylion565",
    "password": "peter1",
    "invokedAt": "2021-11-07T03:58:51.142Z"
  },
  {
    "firstName": "Obbe",
    "lastName": "Burgering",
    "email": "obbe.burgering@example.com",
    "username": "organicbutterfly430",
    "password": "sting",
    "invokedAt": "2021-11-07T04:59:19.528Z"
  },
  {
    "firstName": "رونیکا",
    "lastName": "علیزاده",
    "email": "rwnykh.aalyzdh@example.com",
    "username": "organicmouse845",
    "password": "tttt",
    "invokedAt": "2021-11-07T05:59:08.829Z"
  },
  {
    "firstName": "Burim",
    "lastName": "Hubert",
    "email": "burim.hubert@example.com",
    "username": "heavyostrich899",
    "password": "vinnie",
    "invokedAt": "2021-11-07T06:58:56.540Z"
  },
  {
    "firstName": "Juanita",
    "lastName": "Gordon",
    "email": "juanita.gordon@example.com",
    "username": "beautifulbutterfly485",
    "password": "bailey",
    "invokedAt": "2021-11-07T07:58:50.483Z"
  },
  {
    "firstName": "ماهان",
    "lastName": "حسینی",
    "email": "mhn.hsyny@example.com",
    "username": "heavyrabbit936",
    "password": "banzai",
    "invokedAt": "2021-11-07T08:59:04.207Z"
  },
  {
    "firstName": "Thelma",
    "lastName": "Øvergaard",
    "email": "thelma.overgaard@example.com",
    "username": "silverbird439",
    "password": "supreme",
    "invokedAt": "2021-11-07T09:59:03.707Z"
  },
  {
    "firstName": "Sjur",
    "lastName": "Sandland",
    "email": "sjur.sandland@example.com",
    "username": "silvergoose616",
    "password": "1120",
    "invokedAt": "2021-11-07T10:58:49.469Z"
  },
  {
    "firstName": "Simon",
    "lastName": "Kowalski",
    "email": "simon.kowalski@example.com",
    "username": "organickoala667",
    "password": "poncho",
    "invokedAt": "2021-11-07T11:59:10.662Z"
  },
  {
    "firstName": "Josephine",
    "lastName": "Byrd",
    "email": "josephine.byrd@example.com",
    "username": "lazygorilla187",
    "password": "kevin1",
    "invokedAt": "2021-11-07T13:09:12.965Z"
  },
  {
    "firstName": "Iida",
    "lastName": "Kokko",
    "email": "iida.kokko@example.com",
    "username": "lazybear777",
    "password": "bigred",
    "invokedAt": "2021-11-07T13:58:58.448Z"
  },
  {
    "firstName": "Volkan",
    "lastName": "Abanuz",
    "email": "volkan.abanuz@example.com",
    "username": "happybutterfly698",
    "password": "carolina",
    "invokedAt": "2021-11-07T14:59:13.784Z"
  },
  {
    "firstName": "Odalissa",
    "lastName": "Souza",
    "email": "odalissa.souza@example.com",
    "username": "brownbutterfly661",
    "password": "beatles",
    "invokedAt": "2021-11-07T15:59:02.597Z"
  },
  {
    "firstName": "Erotildes",
    "lastName": "Viana",
    "email": "erotildes.viana@example.com",
    "username": "beautifulmouse686",
    "password": "lefty",
    "invokedAt": "2021-11-07T17:08:20.906Z"
  },
  {
    "firstName": "Alicia",
    "lastName": "Margaret",
    "email": "alicia.margaret@example.com",
    "username": "purplegoose898",
    "password": "phpbb",
    "invokedAt": "2021-11-07T17:58:54.137Z"
  },
  {
    "firstName": "Alberto",
    "lastName": "Black",
    "email": "alberto.black@example.com",
    "username": "greenmeercat836",
    "password": "horney",
    "invokedAt": "2021-11-07T18:58:58.091Z"
  },
  {
    "firstName": "Albert",
    "lastName": "Larsen",
    "email": "albert.larsen@example.com",
    "username": "sadfish539",
    "password": "bettina",
    "invokedAt": "2021-11-07T19:58:59.422Z"
  },
  {
    "firstName": "Caroline",
    "lastName": "Rogers",
    "email": "caroline.rogers@example.com",
    "username": "blackduck972",
    "password": "drive",
    "invokedAt": "2021-11-07T20:59:06.054Z"
  },
  {
    "firstName": "Josias",
    "lastName": "Gomes",
    "email": "josias.gomes@example.com",
    "username": "silverwolf847",
    "password": "madeline",
    "invokedAt": "2021-11-07T21:58:58.677Z"
  }
]