[
  {
    "firstName": "Svetlana",
    "lastName": "Šerbedžija",
    "email": "svetlana.serbedzija@example.com",
    "username": "brownbird762",
    "password": "orion1",
    "invokedAt": "2022-08-01T03:18:56.642Z"
  },
  {
    "firstName": "Morris",
    "lastName": "Boyd",
    "email": "morris.boyd@example.com",
    "username": "angrybird445",
    "password": "ripley",
    "invokedAt": "2022-08-01T05:02:50.959Z"
  },
  {
    "firstName": "Lois",
    "lastName": "Ribeiro",
    "email": "lois.ribeiro@example.com",
    "username": "ticklishelephant579",
    "password": "whocares",
    "invokedAt": "2022-08-01T06:20:37.719Z"
  },
  {
    "firstName": "Pervushko",
    "lastName": "Buhalo",
    "email": "pervushko.buhalo@example.com",
    "username": "sadbutterfly319",
    "password": "carmel",
    "invokedAt": "2022-08-01T07:11:13.248Z"
  }
]