[
  {
    "firstName": "Victoria",
    "lastName": "Olivier",
    "email": "victoria.olivier@example.com",
    "username": "heavylion787",
    "password": "amsterdam",
    "invokedAt": "2022-08-06T02:47:55.635Z"
  },
  {
    "firstName": "Buse",
    "lastName": "Öztürk",
    "email": "buse.ozturk@example.com",
    "username": "beautifulgorilla331",
    "password": "wesley",
    "invokedAt": "2022-08-06T03:37:08.544Z"
  },
  {
    "firstName": "Adina",
    "lastName": "da Conceição",
    "email": "adina.daconceicao@example.com",
    "username": "heavyostrich845",
    "password": "norman",
    "invokedAt": "2022-08-06T04:10:44.024Z"
  },
  {
    "firstName": "Nandita",
    "lastName": "Dsouza",
    "email": "nandita.dsouza@example.com",
    "username": "goldenswan314",
    "password": "hardware",
    "invokedAt": "2022-08-06T04:59:53.488Z"
  },
  {
    "firstName": "Cristobal",
    "lastName": "Salinas",
    "email": "cristobal.salinas@example.com",
    "username": "goldengorilla970",
    "password": "newyork",
    "invokedAt": "2022-08-06T05:59:03.161Z"
  },
  {
    "firstName": "Miroboga",
    "lastName": "Baievskiy",
    "email": "miroboga.baievskiy@example.com",
    "username": "tinyostrich829",
    "password": "cutter",
    "invokedAt": "2022-08-06T06:58:49.446Z"
  },
  {
    "firstName": "Valeriy",
    "lastName": "Podolyaka",
    "email": "valeriy.podolyaka@example.com",
    "username": "silverleopard550",
    "password": "pierce",
    "invokedAt": "2022-08-06T07:59:08.448Z"
  }
]