[
  {
    "firstName": "Dimitri",
    "lastName": "Kirchhof",
    "email": "dimitri.kirchhof@example.com",
    "username": "sadostrich463",
    "password": "pizza",
    "invokedAt": "2022-06-30T03:02:57.519Z"
  },
  {
    "firstName": "Bobby",
    "lastName": "Macrae",
    "email": "bobby.macrae@example.com",
    "username": "organicfrog663",
    "password": "waldo",
    "invokedAt": "2022-06-30T04:24:03.713Z"
  },
  {
    "firstName": "Susie",
    "lastName": "Turner",
    "email": "susie.turner@example.com",
    "username": "redbear192",
    "password": "1986",
    "invokedAt": "2022-06-30T05:14:51.741Z"
  },
  {
    "firstName": "Tahira",
    "lastName": "Kamphuis",
    "email": "tahira.kamphuis@example.com",
    "username": "goldenladybug651",
    "password": "twisted",
    "invokedAt": "2022-06-30T05:58:53.609Z"
  }
]